{
  "2026-04-11": {
    "001": {
      "score": "1:0",
      "result": "胜"
    },
    "002": {
      "score": "3:2",
      "result": "胜"
    },
    "003": {
      "score": "1:1",
      "result": "平"
    },
    "004": {
      "score": "1:2",
      "result": "负"
    },
    "005": {
      "score": "0:2",
      "result": "负"
    },
    "006": {
      "score": "1:0",
      "result": "胜"
    },
    "007": {
      "score": "1:2",
      "result": "负"
    },
    "008": {
      "score": "0:2",
      "result": "负"
    },
    "009": {
      "score": "3:3",
      "result": "平"
    },
    "010": {
      "score": "3:1",
      "result": "胜"
    },
    "011": {
      "score": "1:0",
      "result": "胜"
    },
    "012": {
      "score": "2:1",
      "result": "胜"
    },
    "013": {
      "score": "0:2",
      "result": "负"
    },
    "014": {
      "score": "3:1",
      "result": "胜"
    },
    "015": {
      "score": "0:1",
      "result": "负"
    },
    "016": {
      "score": "1:0",
      "result": "胜"
    },
    "017": {
      "score": "1:2",
      "result": "负"
    },
    "018": {
      "score": "2:2",
      "result": "平"
    },
    "019": {
      "score": "1:0",
      "result": "胜"
    },
    "020": {
      "score": "4:1",
      "result": "胜"
    },
    "021": {
      "score": "2:1",
      "result": "胜"
    },
    "022": {
      "score": "0:3",
      "result": "负"
    },
    "023": {
      "score": "2:0",
      "result": "胜"
    },
    "024": {
      "score": "0:5",
      "result": "负"
    },
    "025": {
      "score": "4:1",
      "result": "胜"
    },
    "026": {
      "score": "0:1",
      "result": "负"
    },
    "027": {
      "score": "2:1",
      "result": "胜"
    },
    "028": {
      "score": "2:1",
      "result": "胜"
    },
    "029": {
      "score": "0:1",
      "result": "负"
    },
    "030": {
      "score": "1:2",
      "result": "负"
    }
  }
}